{
  "nav.home": "Home",
  "nav.write": "Write",
  "nav.content": "Content",
  "nav.preview": "Preview",
  "nav.publish": "Publish",
  "nav.settings": "Settings",
  "sidebar.summary.label": "Server summary",
  "sidebar.summary.version": "Bocchi M6",
  "sidebar.summary.running": "Server is running",
  "sidebar.summary.systemInfo": "System Info",
  "topbar.search.placeholder": "Search posts, pages, notes...",
  "topbar.search.aria": "Search content",
  "topbar.new": "New",
  "topbar.appearance.label": "Appearance",
  "topbar.appearance.aria": "Dashboard dark mode",
  "topbar.language.label": "Language",
  "topbar.language.aria": "Dashboard UI language",
  "topbar.account.aria": "Open users",
  "topbar.logout.aria": "Logout",
  "setup.page.title": "Setup",
  "setup.page.eyebrow": "Welcome / Setup",
  "setup.page.heading": "Initialize Bocchi",
  "setup.page.description": "Create the Admin account and set the site basics shared by Admin and the public frontend.",
  "setup.language.aria": "Setup language",
  "setup.appearance.switchToDark": "Switch to dark mode",
  "setup.appearance.switchToLight": "Switch to light mode",
  "setup.admin.eyebrow": "Step 1",
  "setup.admin.title": "Create the first Admin",
  "setup.site.eyebrow": "Step 2",
  "setup.site.title": "Set the frontend basics",
  "setup.field.username": "Username",
  "setup.field.emailOptional": "Email (optional)",
  "setup.field.email": "Email (optional)",
  "setup.field.displayName": "Display name",
  "setup.field.displayName.placeholder": "Shown inside Admin",
  "setup.field.password": "Password",
  "setup.field.confirmPassword": "Confirm password",
  "setup.field.siteName": "Site name",
  "setup.field.defaultTitle": "Default title",
  "setup.field.defaultTitle.placeholder": "Used when a page has no custom title",
  "setup.field.description": "Description",
  "setup.field.description.placeholder": "A short summary for public display and search",
  "setup.field.publicBaseUrl": "Default frontend URL",
  "setup.field.publicBaseUrl.placeholder": "https://domain.com/",
  "setup.field.defaultThemeId": "Default frontend Theme",
  "setup.field.copyright": "Copyright",
  "setup.field.copyright.placeholder": "Copyright © 2026 Bocchi.",
  "setup.passwordChecklist.aria": "Password requirements",
  "setup.passwordChecklist.length": "At least 8 characters.",
  "setup.passwordChecklist.letter": "Includes a letter.",
  "setup.passwordChecklist.numberOrSymbol": "Includes a number or symbol.",
  "setup.passwordChecklist.match": "Both entries match.",
  "setup.password.toggle": "Show or hide password",
  "setup.passwordStrength.label": "Password strength:",
  "setup.passwordStrength.weak": "Weak",
  "setup.passwordStrength.medium": "Medium",
  "setup.passwordStrength.strong": "Strong",
  "setup.site.note": "These values are saved as Home Server site settings.",
  "setup.action.next": "Next",
  "setup.action.back": "Back",
  "setup.action.finish": "Finish initialization",
  "setup.action.payloadNote": "Keep the Admin account details safe.",
  "setup.action.note": "After completion, the public Setup entry closes and Admin opens.",
  "setup.helper.aria": "Setup notes",
  "setup.helper.badge": "First run",
  "setup.helper.title": "First run",
  "setup.helper.description": "This is the first run of your Bocchi Home Server; Setup initializes the required data.",
  "setup.helper.database": "Local database",
  "setup.helper.databaseText": "Identity, setup state, and site basics are stored in SQLite under DataRoot.",
  "setup.helper.closes": "Setup closes",
  "setup.helper.closesText": "Once the first Admin exists, this page redirects to Admin or Login.",
  "setup.helper.frontend": "Frontend projection",
  "setup.helper.frontendText": "Site basics sync to workspace site.yaml so Generator and Theme input read the same facts.",
  "setup.helper.warning": "Only run Setup on your own server.",
  "setup.error.usernameRequired": "Username is required.",
  "setup.error.emailInvalid": "Email is not valid.",
  "setup.error.emailRequired": "Username is required.",
  "setup.error.passwordLength": "Password must be at least 8 characters.",
  "setup.error.passwordConfirm": "Password confirmation does not match.",
  "setup.error.siteNameRequired": "Site name is required.",
  "setup.error.publicUrlInvalid": "Default frontend URL must be an absolute http or https URL.",
  "setup.error.payloadExpired": "Setup step 1 has expired. Please enter the Admin account again.",
  "home.page.title": "Home",
  "home.page.eyebrow": "Dashboard",
  "home.page.heading": "Site overview",
  "home.page.description": "Review the real content state, open the protected preview, and publish when the checks are clear.",
  "home.summary.aria": "Site overview summary",
  "home.summary.server": "Home Server",
  "home.summary.serverRunning": "Running",
  "home.summary.content": "Content",
  "home.summary.contentFormat": "{0} items",
  "home.summary.lastCheck": "Last check",
  "home.summary.notChecked": "Not checked",
  "home.summary.lastCheckFormat": "Run #{0} · {1}",
  "home.feed.eyebrow": "Content",
  "home.feed.title": "Recent content",
  "home.feed.openContent": "Open Content",
  "home.feed.emptyTitle": "No content is listed yet",
  "home.feed.emptyDescription": "No content has been scanned yet. Create a file or open Content to run the first check.",
  "home.feed.createFirst": "Create content",
  "home.feed.checkContent": "Check content",
  "home.side.aria": "Preview and publishing status",
  "home.preview.title": "Protected preview",
  "home.preview.open": "Open preview",
  "home.preview.description": "The public site preview opens only after Admin login, so setup details and draft checks stay inside Home Server.",
  "home.preview.access": "Access",
  "home.preview.protected": "Admin login required",
  "home.preview.entry": "Entry",
  "home.publish.title": "Publishing status",
  "home.publish.noCheck": "Content check has not run yet",
  "home.publish.noIssues": "Content check has no issues",
  "home.publish.issueFormat": "{0} errors / {1} warnings",
  "home.publish.noContent": "No content projected yet",
  "home.publish.contentFormat": "{0} content items",
  "home.publish.settingsReady": "Site settings are initialized",
  "home.publish.action": "Open Publish",
  "home.status.ready": "Ready",
  "home.status.draft": "Draft",
  "home.status.archived": "Archived",
  "home.action.edit": "Edit",
  "home.action.continue": "Continue",
  "home.scan.succeeded": "Succeeded",
  "home.scan.failed": "Failed",
  "home.scan.running": "Running",
  "settings.page.title": "Settings",
  "settings.page.eyebrow": "Settings",
  "settings.page.heading": "Keep the server clear.",
  "settings.page.description": "Settings stay grouped around everyday publishing work. Deeper system details stay in calm supporting panels.",
  "settings.nav.basic": "Basic Info",
  "settings.nav.localization": "Localization",
  "settings.nav.database": "Database",
  "settings.nav.login": "Third-party Login",
  "settings.nav.theme": "Theme",
  "settings.nav.users": "Users",
  "settings.nav.workspace": "Workspace",
  "settings.localization.title": "Localization",
  "settings.localization.description": "Dashboard language is only your Admin UI preference. Site languages describe the public site and future Theme Context.",
  "settings.localization.dashboardTitle": "Dashboard UI language",
  "settings.localization.dashboardDescription": "Saved in a culture cookie so it can switch the current Admin UI without touching the frontend Theme.",
  "settings.localization.saveUiLanguage": "Use this language",
  "settings.localization.siteTitle": "Site languages",
  "settings.localization.primaryLanguage": "Site primary language",
  "settings.localization.enabledLanguages": "Site enabled languages",
  "settings.localization.searchLanguages": "Find a language",
  "settings.localization.searchLanguagesPlaceholder": "Search code, native name, or English name",
  "settings.localization.selectedLanguages": "Enabled languages",
  "settings.localization.noLanguageResults": "No language matches this search.",
  "settings.localization.disableLanguage": "Disable",
  "settings.localization.urlPolicy": "URL policy",
  "settings.localization.urlPolicyValue": "Primary language has no prefix; other languages use a language prefix.",
  "settings.localization.customTitle": "Custom language",
  "settings.localization.customDescription": "Use this for languages not in the built-in list. Bocchi suggests BCP 47 tags but keeps custom codes editable.",
  "settings.localization.customCode": "Language code",
  "settings.localization.customNativeName": "Native name",
  "settings.localization.customEnglishName": "English name",
  "settings.localization.addCustom": "Add custom language",
  "settings.localization.removeCustom": "Remove",
  "settings.localization.saveSite": "Save site languages",
  "settings.localization.saved": "Saved",
  "settings.localization.needsAttention": "Needs attention",
  "settings.localization.primaryIncluded": "Primary language is always enabled.",
  "settings.localization.customIncomplete": "Custom language needs code, native name, and English name.",
  "settings.localization.customDuplicate": "This language already exists in the picklist.",
  "settings.localization.commonTextTitle": "Common theme text",
  "settings.localization.commonTextDescription": "Optional plain text overrides for shared Theme labels. Leave a field blank to use the Theme default.",
  "settings.localization.commonTextSearch": "Find a text key",
  "settings.localization.commonTextSearchPlaceholder": "Search menu, common, or content keys",
  "settings.localization.commonTextNoResults": "No text key matches this search.",
  "settings.localization.commonTextSave": "Save common text",
  "settings.localization.commonTextSaved": "Common theme text has been saved.",
  "settings.theme.i18nTitle": "Theme private text",
  "settings.theme.i18nDescription": "Optional overrides for private text keys declared by the current Theme manifest.",
  "settings.theme.i18nEmpty": "This Theme does not declare private text keys.",
  "settings.theme.i18nSearch": "Find a Theme key",
  "settings.theme.i18nSearchPlaceholder": "Search key, title, or description",
  "settings.theme.i18nNoResults": "No Theme key matches this search.",
  "settings.theme.i18nSave": "Save Theme text",
  "settings.theme.i18nSaved": "Theme private text has been saved."
}
