{
  "nav.overview": "总览",
  "nav.content": "内容",
  "nav.posts": "文章",
  "nav.notes": "短文",
  "nav.works": "作品",
  "nav.site": "站点",
  "nav.pages": "页面",
  "nav.friends": "友情链接",
  "nav.siteNavigation": "导航栏",
  "nav.themeCustomization": "主题定制",
  "nav.publish": "发布",
  "nav.settings": "设置",
  "nav.open": "打开导航",
  "nav.close": "关闭导航",
  "sidebar.preview.title": "站点预览",
  "sidebar.preview.open": "打开预览",
  "topbar.search.placeholder": "搜索文章、页面、短文…",
  "topbar.search.aria": "搜索内容",
  "topbar.appearance.label": "外观",
  "topbar.appearance.aria": "Dashboard 明暗外观",
  "topbar.appearance.auto": "自动",
  "topbar.appearance.light": "浅色",
  "topbar.appearance.dark": "深色",
  "topbar.language.label": "语言",
  "topbar.language.aria": "Dashboard UI 语言",
  "topbar.account.aria": "打开用户管理",
  "topbar.logout.aria": "退出登录",
  "setup.page.title": "Setup",
  "setup.page.eyebrow": "Welcome / Setup",
  "setup.page.heading": "初始化 Bocchi",
  "setup.page.description": "创建管理员账号，并设置后台与前台共用的站点基础信息。",
  "setup.language.aria": "Setup 语言",
  "setup.appearance.switchToDark": "切换到深色模式",
  "setup.appearance.switchToLight": "切换到浅色模式",
  "setup.admin.eyebrow": "步骤 1",
  "setup.admin.title": "创建第一个 Admin",
  "setup.site.eyebrow": "步骤 2",
  "setup.site.title": "设置前台基础信息",
  "setup.field.username": "用户名",
  "setup.field.emailOptional": "Email（可选）",
  "setup.field.email": "Email（可选）",
  "setup.field.displayName": "显示名",
  "setup.field.displayName.placeholder": "用于管理后台显示",
  "setup.field.password": "密码",
  "setup.field.confirmPassword": "确认密码",
  "setup.field.siteName": "站点名称",
  "setup.field.defaultTitle": "默认标题",
  "setup.field.defaultTitle.placeholder": "页面没有专用标题时使用",
  "setup.field.description": "描述",
  "setup.field.description.placeholder": "用于前台展示和搜索摘要的简短说明",
  "setup.field.publicBaseUrl": "默认前台 URL",
  "setup.field.publicBaseUrl.placeholder": "https://domain.com/",
  "setup.field.defaultThemeId": "默认前台 Theme",
  "setup.field.copyright": "Copyright",
  "setup.field.copyright.placeholder": "Copyright © 2026 Bocchi.",
  "setup.passwordChecklist.aria": "密码要求",
  "setup.passwordChecklist.length": "至少 8 个字符。",
  "setup.passwordChecklist.letter": "包含字母。",
  "setup.passwordChecklist.numberOrSymbol": "包含数字或特殊字符。",
  "setup.passwordChecklist.match": "两次输入一致。",
  "setup.password.toggle": "显示或隐藏密码",
  "setup.passwordStrength.label": "密码强度:",
  "setup.passwordStrength.weak": "弱",
  "setup.passwordStrength.medium": "中",
  "setup.passwordStrength.strong": "强",
  "setup.site.note": "这些信息会作为 Home Server 的站点基础设置保存。",
  "setup.action.next": "下一步",
  "setup.action.back": "返回",
  "setup.action.finish": "完成初始化",
  "setup.action.payloadNote": "请妥善保管管理员账号信息。",
  "setup.action.note": "完成后将关闭公开 Setup 入口，并进入后台。",
  "setup.helper.aria": "Setup 说明",
  "setup.helper.badge": "首次启动",
  "setup.helper.title": "首次运行",
  "setup.helper.description": "这是 Bocchi Home Server 的首次运行。完成设置后，系统会初始化必要数据。",
  "setup.helper.database": "本地数据库",
  "setup.helper.databaseText": "Identity、Setup 状态和站点基础约定存放在 DataRoot 下的 SQLite。",
  "setup.helper.closes": "Setup 会关闭",
  "setup.helper.closesText": "第一个 Admin 创建后，本页会跳转到 Admin 或 Login。",
  "setup.helper.frontend": "前台投影",
  "setup.helper.frontendText": "站点基础信息会同步到 workspace 的 site.yaml，让 Generator 和 Theme 输入读取同一份事实。",
  "setup.helper.warning": "只在你自己的服务器上运行 Setup。",
  "setup.error.usernameRequired": "用户名必填。",
  "setup.error.emailInvalid": "Email 格式不正确。",
  "setup.error.emailRequired": "用户名必填。",
  "setup.error.passwordLength": "密码至少需要 8 个字符。",
  "setup.error.passwordConfirm": "两次输入的密码不一致。",
  "setup.error.siteNameRequired": "站点名称必填。",
  "setup.error.publicUrlInvalid": "默认前台 URL 必须是 http 或 https 绝对 URL。",
  "setup.error.payloadExpired": "Setup 第一步已过期，请重新输入 Admin 账号。",
  "home.page.title": "总览",
  "home.page.eyebrow": "Dashboard",
  "home.page.heading": "下午好，来看看今天写点什么吧。",
  "home.page.description": "起草一句话、丰富一篇文章，或是调整页面与设置。",
  "home.guide.dismiss.aria": "关闭这张引导卡片",
  "home.guide.welcome.title": "欢迎使用 Bocchi",
  "home.guide.welcome.body": "这里是你的后台首页。在这里可以看到最近的创作状态、随手发一条短文，也能随时预览你的站点。",
  "home.guide.welcome.action": "了解一下",
  "home.guide.site-language.title": "设置站点语言",
  "home.guide.site-language.body": "选择前台主要语言与启用的语言列表；Dashboard 本身的语言随时可在顶栏切换。",
  "home.guide.site-language.action": "去设置",
  "home.guide.site-theme.title": "选一个站点主题",
  "home.guide.site-theme.body": "站点面向读者的样子由主题决定。你可以在设置里预览并切换。",
  "home.guide.site-theme.action": "看看主题",
  "home.guide.edit-page.title": "编辑站点页面",
  "home.guide.edit-page.body": "“页面”是长期稳定的内容块，比如“关于”、导航说明或作品索引。现在就可以开始编排。",
  "home.guide.edit-page.action": "打开页面",
  "home.quick.writePost.title": "写文章",
  "home.quick.writePost.subtitle": "打开编辑器，慢慢写一篇长文。",
  "home.quick.writeNote.title": "发短文",
  "home.quick.writeNote.subtitle": "500 字之内快速分享。",
  "home.quick.editPage.title": "编辑页面",
  "home.quick.editPage.subtitle": "整理关于、导航、作品索引等固定页面。",
  "home.quick.publish.title": "发布站点",
  "home.quick.publish.subtitle": "检查运行完后一键导出。",
  "home.composer.aria": "快速发布区",
  "home.composer.tabs.note": "发布短文",
  "home.composer.tabs.post": "发布文章",
  "home.composer.placeholder": "有什么新鲜事？",
  "home.composer.publishNote": "发布",
  "home.composer.publishing": "发布中…",
  "home.composer.counterFormat": "{0} / {1}",
  "home.composer.toolbar.image": "插入图片",
  "home.composer.toolbar.link": "插入链接",
  "home.composer.toolbar.tag": "插入标签",
  "home.composer.toolbar.hash": "插入话题",
  "home.composer.toolbar.emoji": "插入表情",
  "home.composer.toolbar.disabledHint": "该能力还在路上。",
  "home.composer.postEmptyTitle": "文章需要更丰富的编辑体验",
  "home.composer.postEmptyDescription": "点下面的按钮打开完整编辑器，他不会随首页只看一眼的节奏走。",
  "home.composer.openFullEditor": "打开完整编辑器",
  "home.composer.publishFailed": "短文发布失败：{0}",
  "home.preview.title": "站点预览",
  "home.preview.description": "仅管理员可见；公开访问请发布站点。",
  "home.preview.open": "打开预览",
  "home.recent.title": "最近内容",
  "home.recent.viewAll": "查看全部",
  "home.recent.menu": "更多操作",
  "home.recent.emptyTitle": "还没有内容",
  "home.recent.emptyDescription": "开始创作吧，写一篇文章，发表作品，或分享新鲜事？",
  "home.status.ready": "已就绪",
  "home.status.draft": "草稿",
  "home.status.archived": "已归档",
  "home.action.edit": "编辑",
  "home.action.continue": "继续",
  "home.kind.post": "文章",
  "home.kind.note": "短文",
  "home.kind.work": "作品",
  "home.kind.page": "页面",
  "kind.posts.title": "文章",
  "kind.posts.description": "用文章向读者展现你的世界。",
  "kind.notes.title": "短文",
  "kind.notes.description": "照片、感悟、新鲜事，随手分享。",
  "kind.works.title": "作品",
  "kind.works.description": "以作品为单位集中展示的内容。",
  "kind.pages.title": "页面",
  "kind.pages.description": "如“关于”、“友链”这类项终存在的内容页。",
  "kind.index.actions.aria": "内容管理操作",
  "kind.index.actions.create": "创建",
  "kind.index.actions.categories": "类别",
  "kind.index.actions.tags": "标签",
  "kind.index.taxonomy.aria": "分类和标签管理",
  "kind.index.aria.list": "内容列表",
  "kind.index.empty.titleFormat": "暂无{0}内容",
  "kind.index.empty.description": "开始创作吧",
  "kind.index.empty.action": "创建",
  "kind.index.delete": "删除",
  "kind.index.delete.confirm": "确认删除？",
  "kind.index.delete.cancel": "取消",
  "kind.index.delete.confirmAction": "删除",
  "category.editor.eyebrow": "独立类别树",
  "category.editor.title": "类别编辑器",
  "category.editor.maxDepthFormat": "最多 {0} 层",
  "category.editor.addRoot": "添加根类别",
  "category.editor.addChild": "添加子类别",
  "category.editor.depthLimit": "已到最深层",
  "category.editor.remove": "删除类别",
  "category.editor.namePlaceholder": "类别名称",
  "category.editor.slugPlaceholder": "URL slug",
  "category.editor.levelFormat": "{0} 层",
  "category.editor.save": "保存类别",
  "category.editor.saving": "保存中…",
  "category.editor.loading": "正在读取类别…",
  "category.editor.empty": "还没有类别",
  "category.editor.saved": "类别已保存",
  "category.editor.validation.emptyName": "请先填写所有类别名称。",
  "home.scan.succeeded": "成功",
  "home.scan.failed": "失败",
  "home.scan.running": "运行中",
  "settings.page.title": "设置",
  "settings.page.eyebrow": "设置",
  "settings.page.heading": "保持服务器清爽。",
  "settings.page.description": "设置页围绕日常发布组织；更深的系统细节留在安静的辅助面板里。",
  "settings.nav.basic": "基本信息",
  "settings.nav.localization": "本地化",
  "settings.nav.database": "数据库",
  "settings.nav.login": "第三方登录",
  "settings.nav.users": "用户",
  "settings.nav.workspace": "工作区",
  "settings.localization.title": "本地化",
  "settings.localization.description": "Dashboard 语言只是后台 UI 偏好；站点语言描述公开站点和后续 Theme Context。",
  "settings.localization.dashboardTitle": "Dashboard UI 语言",
  "settings.localization.dashboardDescription": "它保存到 culture cookie，只切换当前 Admin UI，不影响前台 Theme。",
  "settings.localization.saveUiLanguage": "使用这个语言",
  "settings.localization.siteTitle": "站点语言",
  "settings.localization.primaryLanguage": "站点主要语言",
  "settings.localization.enabledLanguages": "站点启用语言",
  "settings.localization.searchLanguages": "查找语言",
  "settings.localization.searchLanguagesPlaceholder": "搜索 code、当地名称或英文名称",
  "settings.localization.selectedLanguages": "已启用语言",
  "settings.localization.noLanguageResults": "没有匹配的语言。",
  "settings.localization.disableLanguage": "停用",
  "settings.localization.urlPolicy": "URL 策略",
  "settings.localization.urlPolicyValue": "主语言不加前缀；其他语言使用语言前缀。",
  "settings.localization.customTitle": "自定义语言",
  "settings.localization.customDescription": "用于内置列表没有覆盖的语言。Bocchi 建议使用 BCP 47 tag，但不会拒绝自定义代码。",
  "settings.localization.customCode": "语言代码",
  "settings.localization.customNativeName": "当地语言名称",
  "settings.localization.customEnglishName": "英文名称",
  "settings.localization.addCustom": "添加自定义语言",
  "settings.localization.removeCustom": "移除",
  "settings.localization.saveSite": "保存站点语言",
  "settings.localization.saved": "已保存",
  "settings.localization.needsAttention": "需要处理",
  "settings.localization.primaryIncluded": "主要语言总会保持启用。",
  "settings.localization.customIncomplete": "自定义语言需要填写代码、当地语言名称和英文名称。",
  "settings.localization.customDuplicate": "这个语言已经在 Picklist 中。",
  "settings.localization.commonTextTitle": "Theme 通用文本",
  "settings.localization.commonTextDescription": "为 Theme 共享标签提供可选 plain text 覆盖。留空时继续使用 Theme 默认文本。",
  "settings.localization.commonTextSearch": "查找文本 key",
  "settings.localization.commonTextSearchPlaceholder": "搜索 menu、common 或 content key",
  "settings.localization.commonTextNoResults": "没有匹配的文本 key。",
  "settings.localization.commonTextSave": "保存通用文本",
  "settings.localization.commonTextSaved": "Theme 通用文本已保存。",
  "siteNavigation.page.title": "导航栏",
  "siteNavigation.page.eyebrow": "站点 / 导航栏",
  "siteNavigation.page.heading": "导航栏",
  "siteNavigation.page.description": "编辑前台 primary menu；桌面端、移动端和嵌套展示由当前 Theme 决定。",
  "siteNavigation.editor.title": "Primary Menu",
  "siteNavigation.editor.treeTitle": "Menu tree",
  "siteNavigation.editor.detailTitle": "菜单项详情",
  "siteNavigation.editor.detailEmptyTitle": "选择一个菜单项",
  "siteNavigation.editor.detailEmptyDescription": "从左侧树选择菜单项后编辑目标和文案。",
  "siteNavigation.editor.countFormat": "{0} 项",
  "siteNavigation.editor.selected": "当前选中",
  "siteNavigation.editor.addRoot": "添加根菜单",
  "siteNavigation.editor.addChild": "添加子菜单",
  "siteNavigation.editor.depthLimit": "已到最深层",
  "siteNavigation.editor.remove": "删除菜单",
  "siteNavigation.editor.moveUp": "上移",
  "siteNavigation.editor.moveDown": "下移",
  "siteNavigation.editor.autoLabel": "自动文案",
  "siteNavigation.editor.labelPlaceholder": "菜单文字（留空则使用目标默认值）",
  "siteNavigation.editor.targetLabel": "菜单目标",
  "siteNavigation.editor.labelMode": "文案模式",
  "siteNavigation.editor.labelMode.auto": "自动",
  "siteNavigation.editor.labelMode.autoHelp": "使用目标默认文案。",
  "siteNavigation.editor.labelMode.plain": "普通文本",
  "siteNavigation.editor.labelMode.plainHelp": "所有语言使用同一个固定标签。",
  "siteNavigation.editor.labelMode.siteI18n": "站点 i18n",
  "siteNavigation.editor.labelMode.siteI18nHelp": "使用 Common i18n key，并在本页按站点启用语言填写文案。",
  "siteNavigation.editor.labelMode.themeI18n": "Theme i18n",
  "siteNavigation.editor.labelMode.themeI18nHelp": "此项保留已有 Theme 私有 i18n 引用；Theme 私有文本在主题定制中维护。",
  "siteNavigation.editor.plainLabel": "菜单文字",
  "siteNavigation.editor.i18nKey": "Common i18n key",
  "siteNavigation.editor.i18nKeyPlaceholder": "menu.custom.about",
  "siteNavigation.editor.i18nTextTitle": "各语言文案",
  "siteNavigation.editor.i18nTextPlaceholder": "{0} 文案",
  "siteNavigation.editor.themeI18nKey": "Theme i18n key",
  "siteNavigation.editor.i18nPreviewFormat": "{0}@{1}",
  "siteNavigation.editor.levelFormat": "{0} 层",
  "siteNavigation.editor.save": "保存菜单",
  "siteNavigation.editor.saving": "保存中…",
  "siteNavigation.editor.loading": "正在读取 Menu…",
  "siteNavigation.editor.empty": "还没有菜单项",
  "siteNavigation.editor.saved": "Menu 已保存",
  "siteNavigation.warning.title": "有目标在当前内容或 Theme 下不可用",
  "siteNavigation.warning.unresolvedFormat": "“{0}” 指向 {1}:{2}，公开 Theme input 会跳过这个菜单项。",
  "siteNavigation.target.unavailable": "不可用",
  "siteNavigation.target.group.builtin": "内置页面",
  "siteNavigation.target.group.themePage": "Theme 页面",
  "siteNavigation.target.group.page": "页面",
  "siteNavigation.target.group.postCategory": "文章类别",
  "siteNavigation.target.group.unavailable": "不可用目标",
  "siteNavigation.target.builtin.home": "内置 · 首页",
  "siteNavigation.target.builtin.posts": "内置 · 文章",
  "siteNavigation.target.builtin.works": "内置 · 作品",
  "siteNavigation.target.builtin.notes": "内置 · 札记",
  "siteNavigation.target.builtin.friends": "内置 · 友链",
  "contentEditor.template.label": "页面模板",
  "contentEditor.template.unavailableOptionFormat": "{0}（当前 Theme 不可用）",
  "contentEditor.template.unavailableWarningFormat": "当前页面保存的模板 “{0}” 不在当前 Theme 声明中；保存时会继续保留这个 name。",
  "themeCustomization.page.title": "主题定制",
  "themeCustomization.page.eyebrow": "站点 / Theme",
  "themeCustomization.page.heading": "主题定制",
  "themeCustomization.page.description": "编辑当前前台 Theme 声明的配置项和私有文本。",
  "themeCustomization.loading": "正在读取 Theme 配置…",
  "themeCustomization.config.title": "配置项",
  "themeCustomization.config.empty": "当前 Theme 没有声明可编辑配置项。",
  "themeCustomization.config.save": "保存配置",
  "themeCustomization.config.saving": "保存中…",
  "themeCustomization.config.saved": "Theme 配置已保存。",
  "themeCustomization.field.enabled": "启用",
  "themeCustomization.field.defaultOption": "使用默认值",
  "themeCustomization.meta.title": "当前 Theme",
  "themeCustomization.meta.themeName": "名称",
  "themeCustomization.meta.themeId": "Theme id",
  "themeCustomization.meta.schemaGroups": "配置分组",
  "settings.theme.i18nTitle": "Theme 私有文本",
  "settings.theme.i18nDescription": "覆盖当前 Theme manifest 声明的私有文本 key；留空时继续使用 Theme 默认值。",
  "settings.theme.i18nEmpty": "当前 Theme 没有声明私有文本 key。",
  "settings.theme.i18nSearch": "查找 Theme key",
  "settings.theme.i18nSearchPlaceholder": "搜索 key、标题或描述",
  "settings.theme.i18nNoResults": "没有匹配的 Theme key。",
  "settings.theme.i18nSave": "保存 Theme 文本",
  "settings.theme.i18nSaved": "Theme 私有文本已保存。"
}
